{
  "docusaurus-plugin-content-docs": {
    "default": {
      "path": "/docs",
      "versions": [
        {
          "name": "current",
          "label": "Next",
          "isLast": true,
          "path": "/docs",
          "mainDocId": "introduction",
          "docs": [
            {
              "id": "advanced-guides/introduction",
              "path": "/docs/advanced-guides/introduction"
            },
            {
              "id": "api-guides/authenticating",
              "path": "/docs/api-guides/authenticating",
              "sidebar": "tutorialSidebar"
            },
            {
              "id": "api-guides/importing-into-postman",
              "path": "/docs/api-guides/importing-into-postman",
              "sidebar": "tutorialSidebar"
            },
            {
              "id": "api-guides/index",
              "path": "/docs/api-guides/",
              "sidebar": "tutorialSidebar"
            },
            {
              "id": "api-guides/location-engine",
              "path": "/docs/api-guides/location-engine",
              "sidebar": "tutorialSidebar"
            },
            {
              "id": "chirpstack-guides/migrating-from-helium-console",
              "path": "/docs/chirpstack-guides/migrating-from-helium-console",
              "sidebar": "tutorialSidebar"
            },
            {
              "id": "device-guides/browan-tabs-object-locator-guide",
              "path": "/docs/device-guides/browan-tabs-object-locator-guide",
              "sidebar": "tutorialSidebar"
            },
            {
              "id": "device-guides/index",
              "path": "/docs/device-guides/",
              "sidebar": "tutorialSidebar"
            },
            {
              "id": "device-guides/rak-sticker-guide",
              "path": "/docs/device-guides/rak-sticker-guide",
              "sidebar": "tutorialSidebar"
            },
            {
              "id": "device-guides/sensecap-t1000",
              "path": "/docs/device-guides/sensecap-t1000",
              "sidebar": "tutorialSidebar"
            },
            {
              "id": "device-guides/supported-devices",
              "path": "/docs/device-guides/supported-devices",
              "sidebar": "tutorialSidebar"
            },
            {
              "id": "getting-started/add-a-contact",
              "path": "/docs/getting-started/add-a-contact",
              "sidebar": "tutorialSidebar"
            },
            {
              "id": "getting-started/add-a-device",
              "path": "/docs/getting-started/add-a-device",
              "sidebar": "tutorialSidebar"
            },
            {
              "id": "getting-started/add-a-geofence",
              "path": "/docs/getting-started/add-a-geofence",
              "sidebar": "tutorialSidebar"
            },
            {
              "id": "getting-started/add-an-action",
              "path": "/docs/getting-started/add-an-action",
              "sidebar": "tutorialSidebar"
            },
            {
              "id": "getting-started/index",
              "path": "/docs/getting-started/",
              "sidebar": "tutorialSidebar"
            },
            {
              "id": "getting-started/manage-organisations",
              "path": "/docs/getting-started/manage-organisations",
              "sidebar": "tutorialSidebar"
            },
            {
              "id": "getting-started/managing-a-device",
              "path": "/docs/getting-started/managing-a-device",
              "sidebar": "tutorialSidebar"
            },
            {
              "id": "introduction",
              "path": "/docs/introduction",
              "sidebar": "tutorialSidebar"
            }
          ],
          "draftIds": [],
          "sidebars": {
            "tutorialSidebar": {
              "link": {
                "path": "/docs/introduction",
                "label": "Introduction"
              }
            }
          }
        }
      ],
      "breadcrumbs": true
    }
  }
}